[
    {
        "Name": "Ada",
        "Number": "987654321"
    },
    {
        "Name": "Teddy",
        "Number": "987653523"
    },
    {
        "Name": "asddfffa",
        "Number": "098345345875123423432544q122343342543"
    },
    {
        "Name": "Thomas",
        "Number": "08164431360\u001b[3~"
    },
    {
        "Name": "James",
        "Number": "783573453"
    },
    {
        "Name": "Kings",
        "Number": "35645732"
    },
    {
        "Name": "Dominion",
        "Number": "12631254"
    },
    {
        "Name": "Sancho",
        "Number": "43873654798"
    },
    {
        "Name": "Rucky",
        "Number": "897655434"
    },
    {
        "Name": "Chris",
        "Number": "32453456"
    }
]